params_proto/__init__.py
params_proto/app.py
params_proto/documentation.py
params_proto/envvar.py
params_proto/parse_env_template.py
params_proto/proto.py
params_proto/type_utils.py
params_proto/cli/__init__.py
params_proto/cli/ansi_help.py
params_proto/cli/cli_parse.py
params_proto/cli/help_gen.py
params_proto/hyper/__init__.py
params_proto/hyper/proxies.py
params_proto/hyper/sweep.py
params_proto/v1/__init__.py
params_proto/v1/hyper.py
params_proto/v1/params_proto.py
params_proto/v2/__init__.py
params_proto/v2/hyper.py
params_proto/v2/partial.py
params_proto/v2/proto.py
params_proto/v2/utils.py
params_proto-3.2.1.dist-info/METADATA
params_proto-3.2.1.dist-info/WHEEL
params_proto-3.2.1.dist-info/licenses/LICENSE.md
params_proto-3.2.1.dist-info/RECORD
