Metadata-Version: 2.4
Name: params-proto
Version: 3.2.1
Summary: Modern Hyper Parameter Management for Machine Learning
Project-URL: Homepage, https://github.com/geyang/params-proto
Project-URL: Documentation, https://params-proto.readthedocs.io
Project-URL: Repository, https://github.com/geyang/params-proto
Project-URL: Bug Tracker, https://github.com/geyang/params-proto/issues
Author: Ge Yang
License: MIT
License-File: LICENSE.md
Keywords: argcomplete,argparse,argument parser,auto-completion,autocomplete,decorator,hyperparameter,machine learning,params_proto,shell arguments
Classifier: Development Status :: 4 - Beta
Classifier: Intended Audience :: Science/Research
Classifier: Programming Language :: Python :: 3
Classifier: Programming Language :: Python :: 3.8
Classifier: Programming Language :: Python :: 3.9
Classifier: Programming Language :: Python :: 3.10
Classifier: Programming Language :: Python :: 3.11
Classifier: Programming Language :: Python :: 3.12
Requires-Python: >=3.8
Requires-Dist: argcomplete
Requires-Dist: argparse
Requires-Dist: expandvars
Requires-Dist: termcolor
Requires-Dist: waterbear>=2.6.8
Provides-Extra: dev
Requires-Dist: pandas; extra == 'dev'
Requires-Dist: pytest; extra == 'dev'
Requires-Dist: pytest-xdist; extra == 'dev'
Requires-Dist: restructuredtext-lint; extra == 'dev'
Requires-Dist: ruff; extra == 'dev'
Requires-Dist: twine; extra == 'dev'
Provides-Extra: docs
Requires-Dist: furo; extra == 'docs'
Requires-Dist: myst-parser; extra == 'docs'
Requires-Dist: sphinx-autobuild; extra == 'docs'
Requires-Dist: sphinx-copybutton; extra == 'docs'
Requires-Dist: sphinx>=4.0; extra == 'docs'
Requires-Dist: tomli>=1.1.0; (python_version < '3.11') and extra == 'docs'
